leftpad/__init__.py
leftpadx-0.0.1.dist-info/LICENSE
leftpadx-0.0.1.dist-info/METADATA
leftpadx-0.0.1.dist-info/WHEEL
leftpadx-0.0.1.dist-info/top_level.txt
leftpadx-0.0.1.dist-info/RECORD
